factor_analyzer/__init__.py
factor_analyzer/analyze.py
factor_analyzer/confirmatory_factor_analyzer.py
factor_analyzer/factor_analyzer.py
factor_analyzer/rotator.py
factor_analyzer/test_utils.py
factor_analyzer/utils.py
factor_analyzer-0.3.1.dist-info/LICENSE
factor_analyzer-0.3.1.dist-info/METADATA
factor_analyzer-0.3.1.dist-info/WHEEL
factor_analyzer-0.3.1.dist-info/entry_points.txt
factor_analyzer-0.3.1.dist-info/top_level.txt
factor_analyzer-0.3.1.dist-info/zip-safe
factor_analyzer-0.3.1.dist-info/RECORD
