Metadata-Version: 2.1
Name: factor-analyzer
Version: 0.3.1
Summary: A Factor Analysis class
Home-page: https://github.com/EducationalTestingService/factor_analyzer
Author: Jeremy Biggs
Author-email: jbiggs@ets.org
License: UNKNOWN
Keywords: factor analysis
Platform: UNKNOWN
Classifier: Intended Audience :: Science/Research
Classifier: Intended Audience :: Developers
Classifier: Programming Language :: Python
Classifier: Topic :: Scientific/Engineering
Classifier: Operating System :: Microsoft :: Windows
Classifier: Operating System :: POSIX
Classifier: Operating System :: Unix
Classifier: Operating System :: MacOS
Classifier: Programming Language :: Python :: 3
Classifier: Programming Language :: Python :: 3.4
Classifier: Programming Language :: Python :: 3.5
Classifier: Programming Language :: Python :: 3.6
Requires-Dist: pandas
Requires-Dist: scipy
Requires-Dist: numpy
Requires-Dist: scikit-learn
